aind_metadata_cli/__init__.py
aind_metadata_cli/app.py
aind_metadata_cli-0.1.3.dist-info/licenses/LICENSE
aind_metadata_cli-0.1.3.dist-info/METADATA
aind_metadata_cli-0.1.3.dist-info/WHEEL
aind_metadata_cli-0.1.3.dist-info/entry_points.txt
aind_metadata_cli-0.1.3.dist-info/top_level.txt
aind_metadata_cli-0.1.3.dist-info/RECORD
